odoo/addons/sale_timesheet_invoice_link/README.rst
odoo/addons/sale_timesheet_invoice_link/__init__.py
odoo/addons/sale_timesheet_invoice_link/__manifest__.py
odoo/addons/sale_timesheet_invoice_link/i18n/it.po
odoo/addons/sale_timesheet_invoice_link/i18n/sale_timesheet_invoice_link.pot
odoo/addons/sale_timesheet_invoice_link/readme/CONFIGURE.md
odoo/addons/sale_timesheet_invoice_link/readme/CONTEXT.md
odoo/addons/sale_timesheet_invoice_link/readme/CONTRIBUTORS.md
odoo/addons/sale_timesheet_invoice_link/readme/DESCRIPTION.md
odoo/addons/sale_timesheet_invoice_link/readme/ROADMAP.md
odoo/addons/sale_timesheet_invoice_link/readme/USAGE.md
odoo/addons/sale_timesheet_invoice_link/static/description/icon.png
odoo/addons/sale_timesheet_invoice_link/static/description/index.html
odoo/addons/sale_timesheet_invoice_link/views/account_analytic_line_view.xml
odoo_addon_sale_timesheet_invoice_link-18.0.1.0.1.dist-info/METADATA
odoo_addon_sale_timesheet_invoice_link-18.0.1.0.1.dist-info/WHEEL
odoo_addon_sale_timesheet_invoice_link-18.0.1.0.1.dist-info/top_level.txt
odoo_addon_sale_timesheet_invoice_link-18.0.1.0.1.dist-info/RECORD
